redisfacade/__init__.py
redisfacade/facade.py
redisfacade/singleton.py
redisfacade-1.0.7.dist-info/LICENSE
redisfacade-1.0.7.dist-info/METADATA
redisfacade-1.0.7.dist-info/WHEEL
redisfacade-1.0.7.dist-info/top_level.txt
redisfacade-1.0.7.dist-info/RECORD
