Metadata-Version: 2.1
Name: redisfacade
Version: 1.0.7
Summary: A package to implement a facade for accessing Redis databases
Home-page: https://github.com/amedinag32/redisfacade
Author: Alan Medina
Author-email: amedina.escom@hotmail.com
License: UNKNOWN
Platform: UNKNOWN
Classifier: Programming Language :: Python :: 3
Classifier: License :: OSI Approved :: MIT License
Classifier: Operating System :: OS Independent
Requires-Python: >=3.8
Requires-Dist: redis (==5.2.1)
